{
    "cartelas": [
        {
            "id": 1,
            "numbers": [
                [ 3, 18, 33, 50, 67 ],
                [ 9, 22, 38, 55, 71 ],
                [ 12, 27, 0, 59, 74 ],
                [ 6, 19, 41, 48, 63 ],
                [ 14, 29, 44, 52, 69 ]
            ]
        },
        {
            "id": 2,
            "numbers": [
                [ 5, 17, 32, 47, 65 ],
                [ 10, 24, 39, 54, 70 ],
                [ 13, 28, 0, 58, 73 ],
                [ 7, 20, 42, 49, 64 ],
                [ 15, 30, 45, 53, 75 ]
            ]
        },
        {
            "id": 3,
            "numbers": [
                [ 2, 16, 31, 46, 61 ],
                [ 8, 21, 36, 51, 68 ],
                [ 11, 26, 0, 57, 72 ],
                [ 4, 19, 40, 48, 62 ],
                [ 1, 25, 43, 52, 66 ]
            ]
        },
        {
            "id": 4,
            "numbers": [
                [ 3, 18, 34, 50, 69 ],
                [ 9, 23, 38, 55, 71 ],
                [ 12, 27, 0, 59, 74 ],
                [ 6, 20, 41, 48, 63 ],
                [ 14, 29, 44, 52, 67 ]
            ]
        },
        {
            "id": 5,
            "numbers": [
                [ 5, 17, 33, 47, 65 ],
                [ 10, 24, 39, 54, 70 ],
                [ 13, 28, 0, 58, 73 ],
                [ 7, 21, 42, 49, 64 ],
                [ 15, 30, 45, 53, 75 ]
            ]
        }
    ]
}